LICENSE
MANIFEST.in
Makefile
README
setup.cfg
setup.py
tiddlyspace
test/__init__.py
test/__init__.pyc
test/fixtures.py
test/fixtures.pyc
test/httptest.yaml
test/test_compile.py
test/test_determine_space.py
test/test_friendly_uri.py
test/test_jsonp.py
test/test_mapspace.py
test/test_mapuser_validate.py
test/test_privacy.py
test/test_put_hash.py
test/test_safe_mode.py
test/test_search.py
test/test_space_handler.py
test/test_space_link.py
test/test_space_object.py
test/test_space_uri.py
test/test_subscription.py
test/test_user.py
test/test_web.py
test/test_web_clean1.py
test/test_web_cors_headers.py
test/test_web_finger.py
test/test_web_htmljavascript.py
test/test_web_http_api.py
test/test_web_status.py
test/test_web_tiddler_url.py
test/test_web_use_instance.py
test/__pycache__/test_compile.cpython-27-PYTEST.pyc
test/__pycache__/test_determine_space.cpython-27-PYTEST.pyc
test/__pycache__/test_friendly_uri.cpython-27-PYTEST.pyc
test/__pycache__/test_jsonp.cpython-27-PYTEST.pyc
test/__pycache__/test_mapspace.cpython-27-PYTEST.pyc
test/__pycache__/test_mapuser_validate.cpython-27-PYTEST.pyc
test/__pycache__/test_privacy.cpython-27-PYTEST.pyc
test/__pycache__/test_put_hash.cpython-27-PYTEST.pyc
test/__pycache__/test_safe_mode.cpython-27-PYTEST.pyc
test/__pycache__/test_search.cpython-27-PYTEST.pyc
test/__pycache__/test_space_handler.cpython-27-PYTEST.pyc
test/__pycache__/test_space_link.cpython-27-PYTEST.pyc
test/__pycache__/test_space_object.cpython-27-PYTEST.pyc
test/__pycache__/test_space_uri.cpython-27-PYTEST.pyc
test/__pycache__/test_subscription.cpython-27-PYTEST.pyc
test/__pycache__/test_user.cpython-27-PYTEST.pyc
test/__pycache__/test_web.cpython-27-PYTEST.pyc
test/__pycache__/test_web_clean1.cpython-27-PYTEST.pyc
test/__pycache__/test_web_cors_headers.cpython-27-PYTEST.pyc
test/__pycache__/test_web_finger.cpython-27-PYTEST.pyc
test/__pycache__/test_web_htmljavascript.cpython-27-PYTEST.pyc
test/__pycache__/test_web_http_api.cpython-27-PYTEST.pyc
tiddlywebplugins.tiddlyspace.egg-info/PKG-INFO
tiddlywebplugins.tiddlyspace.egg-info/SOURCES.txt
tiddlywebplugins.tiddlyspace.egg-info/dependency_links.txt
tiddlywebplugins.tiddlyspace.egg-info/namespace_packages.txt
tiddlywebplugins.tiddlyspace.egg-info/not-zip-safe
tiddlywebplugins.tiddlyspace.egg-info/requires.txt
tiddlywebplugins.tiddlyspace.egg-info/top_level.txt
