Metadata-Version: 1.0
Name: tiddlywebplugins.tiddlyspace
Version: 1.2.26
Summary: A discoursive social model for Tiddlers
Home-page: http://pypi.python.org/pypi/tiddlywebplugins.tiddlyspace
Author: Osmosoft
Author-email: tiddlyspace@osmosoft.com
License: BSD
Platform: Posix; MacOS X; Windows
